aevolo/__init__.py
aevolo/crossover/__init__.py
aevolo/crossover/abc.py
aevolo/evolver/__init__.py
aevolo/evolver/abc.py
aevolo/evolver/ga.py
aevolo/evolver/test_ga.py
aevolo/generation/__init__.py
aevolo/generation/abc.py
aevolo/individual/__init__.py
aevolo/individual/abc.py
aevolo/mutator/__init__.py
aevolo/mutator/abc.py
aevolo/selector/__init__.py
aevolo/selector/abc.py
aevolo-0.2.1.dist-info/LICENSE
aevolo-0.2.1.dist-info/METADATA
aevolo-0.2.1.dist-info/WHEEL
aevolo-0.2.1.dist-info/top_level.txt
aevolo-0.2.1.dist-info/RECORD
