Metadata-Version: 2.2
Name: aevolo
Version: 0.2.1
Summary: An Evolutionary Algoirthm Framework
Author-email: Ruta <rutatangpersonal@gmail.com>
License: MIT
Project-URL: Homepage, https://github.com/RutaTang/Aevolo
Project-URL: Source, https://github.com/RutaTang/Aevolo
Project-URL: Issues, https://github.com/RutaTang/Aevolo/issues
Keywords: evolutionary-algorithm
Requires-Python: >=3.12
License-File: LICENSE
